fujielab/moshi/moshi_client_lib.py
fujielab/moshi/simple_moshi_client.py
fujielab_moshi_client-0.1.2.dist-info/licenses/LICENSE
fujielab_moshi_client-0.1.2.dist-info/METADATA
fujielab_moshi_client-0.1.2.dist-info/WHEEL
fujielab_moshi_client-0.1.2.dist-info/top_level.txt
fujielab_moshi_client-0.1.2.dist-info/RECORD
