Metadata-Version: 2.4
Name: fujielab-moshi-client
Version: 0.1.2
Summary: Fujie lab. version of Moshi client library for Python programs.
Author-email: Shinya Fujie <shinya.fujie@p.chibakoudai.jp>
License:                                  Apache License
Project-URL: Homepage, https://github.com/fujielab/fujielab-moshi-client
Requires-Python: >=3.8
License-File: LICENSE
Requires-Dist: websockets
Requires-Dist: sounddevice
Requires-Dist: numpy
Requires-Dist: opuslib
Requires-Dist: soxr
Requires-Dist: janus
Dynamic: license-file
